termgraph/__init__.py
termgraph/args.py
termgraph/chart.py
termgraph/constants.py
termgraph/data.py
termgraph/module.py
termgraph/termgraph.py
termgraph/utils.py
termgraph-0.7.5.dist-info/METADATA
termgraph-0.7.5.dist-info/WHEEL
termgraph-0.7.5.dist-info/entry_points.txt
termgraph-0.7.5.dist-info/licenses/LICENSE.txt
termgraph-0.7.5.dist-info/RECORD
