Metadata-Version: 2.4
Name: termgraph
Version: 0.7.5
Summary: A command-line tool that draws basic graphs in the terminal.
Project-URL: Homepage, https://github.com/mkaz/termgraph
Project-URL: Repository, https://github.com/mkaz/termgraph
Project-URL: Issues, https://github.com/mkaz/termgraph/issues
Project-URL: Changelog, https://github.com/mkaz/termgraph/releases
Author-email: mkaz <marcus@mkaz.com>
Maintainer-email: mkaz <marcus@mkaz.com>
License-Expression: MIT
License-File: LICENSE.txt
Keywords: CLI,drawing,graphs,python,shell,terminal,tool,visualization
Classifier: Development Status :: 5 - Production/Stable
Classifier: Environment :: Console
Classifier: Intended Audience :: Developers
Classifier: License :: OSI Approved :: MIT License
Classifier: Natural Language :: English
Classifier: Operating System :: MacOS :: MacOS X
Classifier: Operating System :: POSIX
Classifier: Programming Language :: Python
Classifier: Programming Language :: Python :: 3.9
Classifier: Programming Language :: Python :: 3.10
Classifier: Programming Language :: Python :: 3.11
Classifier: Programming Language :: Python :: 3.12
Classifier: Topic :: Software Development :: Libraries :: Python Modules
Classifier: Topic :: Utilities
Requires-Python: >=3.9
Requires-Dist: colorama>=0.4.6
